{
  "title": "Professional Services",
  "items": [
    {
      "type": "membership",
      "title": "Membership",
      "details": [
        {
          "category": "International",
          "subdetails": [
            "Institute of Operations Research and Management Science (INFORMS) - Senior Member",
            "Association for Computing Machinery (ACM)",
            "Academy of Management (AOM)",
            "Decision Sciences Institute (DSI)",
            "Institute of Electrical and Electronics Engineers (IEEE)",
            "Industry Studies Association (ISA)",
            "Production and Operations Management Society (POMS)"
          ]
        },
        {
          "category": "Korean",
          "subdetails": [
            "KASBA (Management)",
            "KDMS (Data Mining)",
            "KIIE (Industrial Engineering)",
            "KMIS (Information Systems)",
            "KOPOMS (Operations Management)",
            "KORMS (Operations Research and Management Science)",
            "KOSIME (Technology Management)",
            "KrAIS (Information Systems)"
          ]
        }
      ]
    },
    {
      "type": "conference",
      "title": "Conference",
      "details": [
        {
          "category": "Leadership",
          "subdetails": [
            "AOM OSCM Regional Ambassador for Asia 2025-Present",
            "INFORMS TIMES Past President 2025",
            "INFORMS TIMES President 2024",
            "INFORMS TIMES President-Elect 2023",
            "INFORMS TIMES VP of Programs 2022",
            "INFORMS TIMES VP of Membership and Communications 2021"
          ]
        },
        {
          "category": "Track Chair",
          "subdetails": [
            "INFORMS Annual Meeting TIME/NPD 2022",
            "INFORMS Annual Meeting NPD 2021"
          ]
        },
        {
          "category": "Session Chair",
          "subdetails": [
            "INFORMS Annual Meeting 2020, 2019, 2017",
            "POMS Annual Meeting 2019, 2016"
          ]
        },
        {
          "category": "Program Committee",
          "subdetails": [
            "European Conference of Artifical Intelligence (ECAI) 2024-2025",
            "INFORMS MSOM Conference 2024",
            "Pacific Asia Conference on Information Systems (PACIS) 2017"
          ]
        }
      ]
    },
    {
      "type": "service",
      "title": "University Service",
      "details": [
        {
          "category": "Seoul National University",
          "subdetails": [
            "SNU College Curriculum Revision Subcommittee 2026-2028",
            "University Academic Affairs Committee 2023-2025",
            "University Research Committee 2023-2024",
            "AI-X Curriculum Committee 2021-2023",
            "Samsung Research-SNU Project Committee 2022",
            "Various Graduate School of Data Science Committees 2021-2025"
          ]
        },
        {
          "category": "The Ohio State University",
          "subdetails": [
            "Analytics Curriculum Committee 2020-2021",
            "Faculty Recruiting Committee 2018"
          ]
        }
      ]
    },
    {
      "type": "reviewer",
      "title": "Editorial Review Board",
      "details": [
        {
          "category": "Journals",
          "subdetails": [
            "Decision Sciences Journal (DSJ) 2022-Present",
            "Journal of Operations Management (JOM) 2022-Present"
          ]
        }
      ]
    },
    {
      "type": "reviewer",
      "title": "Ad-hoc Reviewer",
      "details": [
        {
          "category": "Journals",
          "subdetails": [
            "Decision Sciences Journal (DSJ)",
            "Decision Support Systems (DSS)",
            "European Journal of Operations Research (EJOR)",
            "IEEE Transactions on Engineering Management (TEM)",
            "IEEE Transactions on Visualization and Computer Graphics (TVCG)",
            "Industry and Innovation",
            "Information & Management",
            "INFORMS Journal on Computing (IJOC)",
            "International Journal on Human-Computer Interaction (IJHCI)",
            "International Journal of Production Research (IJPR)",
            "Journal of Business Logistics (JBL)",
            "Journal of International Business Studies (JIBS)",
            "Journal of Machine Learning Research (JMLR)",
            "Journal of Operations Management (JOM)",
            "Journal of Technology Transfer (JOTT)",
            "Journal of Supply Chain Management (JSCM)",
            "Production and Operations Management (POM)",
            "Research Policy (RP)",
            "Service Science",
            "Strategic Management Journal (SMJ)"
          ]
        },
        {
          "category": "Conferences",
          "subdetails": [
            "Academy of Management Conference (AOM)",
            "ACM SIGCHI Conference (CHI)",
            "ACM SIGIR Conference (SIGIR)",
            "Decision Sciences Institute (DSI)",
            "Hawaii International Conference on System Sciences (HICSS)",
            "International Conference on Learning Representations (ICLR)",
            "IEEE Technology and Engineering Management Conference (TEMSCON)",
            "IEEE Visualization Conference (VIS)",
            "International Conference on Information Systems (ICIS)"
          ]
        }
      ]
    }
  ]
}